{"data":{"site":{"siteMetadata":{"description":"Die Helpmekaar Plan is beplan vir daardie middelklasgroep in ons gemeenskap wat nie kan reken op sosio-ekonomiese hulp van die regering of NGO’s tydens die depressie wat voorlê nie. Ons debietorders hop. Ons verloor ons werk. Ons besighede maak toe. Ons rekenings is agter. Ons versekering verval. Ons verbande en voertuie word nie betaal nie en sal mettertyd deur finansiers teruggeneem word vir ‘n appel en ‘n ei. Baie van ons gaan binnekort nie meer kos hê vir onsself en ons kinders nie. Sonder dat dit sigbaar is na buite, gaan ons mekaar help; gaan ons saam, baie hard baklei vir ons oorlewing.\nGeen welsyn of liefdadigheid nie maar wedersydse lojaliteit en hulp. Binne ons groep help ons mekaar en baklei ons saam vir oorlewing. Sonder die groep staan u alleen en sal u waarskynlik ondergaan. Daarom word u en u familie en vriende hartlik uitgenooi om by ons groep in te skakel. Hoe meer ons is, hoe sterker sal ons wees! Saam gaan ons met trots en waardigheid anderkant uitkom!\nEk sal in die volgende post die onderskeie komponente van die plan uiteensit. Dit staan u vry om daarop te reageer en ‘n bydrae te lewer.","commonKeywords":["expatty","expats","directory","living in Spain","things to do","events","andalusia","listings","attractions","day trips","travel","accommodation","destinations","property","entertainment","business","economy","health","beauty","flora","fauna","news","media","photography","government","tourism","living in Andalucia","society","culture","history","sports","recreation","internet","communication","arts","crafts","education","Sevilla","Malaga","Granada","Cordoba","Almeria","Cadiz","Jaen","Huelva","Costa del Sol","de la Luz","Tropical","Andalucia","Spain"]}}},"pageContext":{}}