{"data":{"site":{"siteMetadata":{"googleMapsKey":"AIzaSyAP0ZUeb4FiNs5Amt-PFKovfVGL5WbxWGE","commonKeywords":["besigheid","afrikaans","suid-afrika","besighede"]}},"markdownRemark":{"id":"481d9df2-096f-50d3-b6fc-f014a137dfa5","html":"<p>Located close to the beautiful Do침ana nature park and Sevilla. This course was formerly called La Rocina. This is a 9-hole course with a  long and difficult 5 pairs, wide undulating greens of modern design and four strategically placed lakes, which give the game an eye-catching and entertaining edge.</p>","frontmatter":{"title":"Club De Golf Las Minas","description":"Club De Golf Las Minas - Located close to the beautiful Do침ana nature park and Sevilla. This course was formerly called La Rocina. This is a 9-hole course with a  long and difficult 5 pairs, wide undulating greens of modern design and four strategically placed lakes, which give the game an eye-catching and entertaining edge. Suitable for all players.","image":"https://source.unsplash.com/h7aVq-7FfPw/1600x400","website":null,"tel":"+34 955 750 678","hours":null,"email":null,"address":"Urb. Las Minas Golf. Buz칩n, 71., Ctra. Isla Mayor Km. 0,800, 41849 Aznalc치zar, Seville, Spain","price":"Highest green fee weekdays 20.00 euros, Highest green fee weekends 20.00 euros","coordinates":[37.296276,-6.234843],"tags":["Golf","Sevilla"]}},"categories":{"edges":[{"node":{"frontmatter":{"tag":"Afslaer","name":"Afslaer","icon":["U+1F4E3"]},"fields":{"slug":"/categories/afslaer/"}}}]}},"pageContext":{"slug":"/spain/andalusia/1566-club-de-golf-las-minas/"}}